neonball/__init__.py
neonball/neonball.py
neonball-0.0.4.dist-info/licenses/LICENSE.txt
neonball-0.0.4.dist-info/METADATA
neonball-0.0.4.dist-info/WHEEL
neonball-0.0.4.dist-info/top_level.txt
neonball-0.0.4.dist-info/RECORD
