Metadata-Version: 2.4
Name: neonball
Version: 0.0.4
Summary: DESCRIPTION
Author-email: Dr Anna Sung and Prof Kelvin Leong <k.leong@chester.ac.uk>
License: BSD-3-Clause
Keywords: Sentiment,text analysis
Classifier: Programming Language :: Python :: 3
Classifier: License :: OSI Approved :: MIT License
Classifier: Operating System :: OS Independent
Requires-Python: >=3.8
License-File: LICENSE.txt
Requires-Dist: sentence-transformers
Requires-Dist: pandas
Requires-Dist: openpyxl
Requires-Dist: ipywidgets
Requires-Dist: matplotlib
Requires-Dist: nltk
Dynamic: license-file
